{
    "Code": 200,
    "Data": {
        "Count": 705,
        "Posts": [
            {
                "Id": 0,
                "PostId": "1123176879843446784",
                "RecruitPostId": 48075,
                "RecruitPostName": "CSIG16-python高级研发工程师",
                "CountryName": "中国",
                "LocationName": "北京",
                "BGName": "CSIG",
                "ProductName": "",
                "CategoryName": "技术",
                "Responsibility": "1.负责地理数据采集平台核心系统/模块的设计和研发；\n2.负责关键技术调研和设计实现；\n3.负责相关系统或模块文档的撰写。",
                "LastUpdateTime": "2019年10月22日",
                "PostURL": "http://careers.tencent.com/jobdesc.html?postId=1123176879843446784",
                "SourceID": 1,
                "IsCollect": false,
                "IsValid": true
            },
            {
                "Id": 0,
                "PostId": "1123175387476529152",
                "RecruitPostId": 42460,
                "RecruitPostName": "25923-Python高级工程师（深圳）",
                "CountryName": "中国",
                "LocationName": "深圳",
                "BGName": "IEG",
                "ProductName": "",
                "CategoryName": "技术",
                "Responsibility": "负责腾讯蓝鲸PaaS后台设计与开发；\r\n负责腾讯游戏运维支撑相关重点SaaS后台设计与开发；\r\n负责腾讯蓝鲸容器管理平台产品后台设计与开发。",
                "LastUpdateTime": "2019年10月12日",
                "PostURL": "http://careers.tencent.com/jobdesc.html?postId=1123175387476529152",
                "SourceID": 1,
                "IsCollect": false,
                "IsValid": true
            },
            {
                "Id": 0,
                "PostId": "1123175931045744640",
                "RecruitPostId": 46007,
                "RecruitPostName": "25923-Python高级工程师（上海）",
                "CountryName": "中国",
                "LocationName": "上海",
                "BGName": "IEG",
                "ProductName": "",
                "CategoryName": "技术",
                "Responsibility": "负责腾讯蓝鲸PaaS后台设计与开发；\n负责腾讯游戏运维支撑相关重点SaaS后台设计与开发；\n负责腾讯蓝鲸容器管理平台产品后台设计与开发。",
                "LastUpdateTime": "2019年10月12日",
                "PostURL": "http://careers.tencent.com/jobdesc.html?postId=1123175931045744640",
                "SourceID": 1,
                "IsCollect": false,
                "IsValid": true
            },
            {
                "Id": 0,
                "PostId": "1158222216970637312",
                "RecruitPostId": 52324,
                "RecruitPostName": "TEG13-python爬虫开发工程师",
                "CountryName": "中国",
                "LocationName": "深圳",
                "BGName": "TEG",
                "ProductName": "",
                "CategoryName": "技术",
                "Responsibility": "负责通用自助爬取平台、分布式实时爬虫服务的架构设计与开发\n优化系统反爬、多渠道抓取和分析、内容提取等能力，从而提升抓取的效率和质量",
                "LastUpdateTime": "2019年10月02日",
                "PostURL": "http://careers.tencent.com/jobdesc.html?postId=1158222216970637312",
                "SourceID": 1,
                "IsCollect": false,
                "IsValid": true
            },
            {
                "Id": 0,
                "PostId": "1178502235433209856",
                "RecruitPostId": 53873,
                "RecruitPostName": "25923-监控系统开发工程师（Python）（深圳）",
                "CountryName": "中国",
                "LocationName": "深圳",
                "BGName": "IEG",
                "ProductName": "",
                "CategoryName": "技术",
                "Responsibility": "负责腾讯游戏监控告警平台后的设计与开发；\n负责监控自有链路采集与采集器框架开发功能；\n参与代码评审和代码开源改造。",
                "LastUpdateTime": "2019年09月30日",
                "PostURL": "http://careers.tencent.com/jobdesc.html?postId=0",
                "SourceID": 1,
                "IsCollect": false,
                "IsValid": true
            },
            {
                "Id": 0,
                "PostId": "1177069667957608448",
                "RecruitPostId": 53746,
                "RecruitPostName": "TEG02-python开发工程师",
                "CountryName": "中国",
                "LocationName": "深圳",
                "BGName": "TEG",
                "ProductName": "",
                "CategoryName": "技术",
                "Responsibility": "负责网络运营DevOps平台的规划设计及开发维护，参与开发文档撰写、代码编写、调试维护等工作，并协助其他开发人员解决技术问题；\n深入理解业务需求，并与运营人员共同对业务模型进行汇总提炼，参与系统建模工作；\n在保障系统的稳定性，可维护性的基础上，快速响应业务需求；",
                "LastUpdateTime": "2019年09月26日",
                "PostURL": "http://careers.tencent.com/jobdesc.html?postId=0",
                "SourceID": 1,
                "IsCollect": false,
                "IsValid": true
            },
            {
                "Id": 0,
                "PostId": "1177067264646582272",
                "RecruitPostId": 53743,
                "RecruitPostName": "25923-数据分析平台开发工程师（Python）（深圳）",
                "CountryName": "中国",
                "LocationName": "深圳",
                "BGName": "IEG",
                "ProductName": "",
                "CategoryName": "技术",
                "Responsibility": "参与腾讯游戏数据平台元数据管理系统的开发；\r\n参与腾讯游戏数据平台数据质量、数据流监控的开发；\r\n参与腾讯游戏数据平台数据分析模块的开发。",
                "LastUpdateTime": "2019年09月26日",
                "PostURL": "http://careers.tencent.com/jobdesc.html?postId=0",
                "SourceID": 1,
                "IsCollect": false,
                "IsValid": true
            },
            {
                "Id": 0,
                "PostId": "1163296010936520704",
                "RecruitPostId": 52697,
                "RecruitPostName": "TME-腾讯音乐python开发工程师（深圳）",
                "CountryName": "中国",
                "LocationName": "深圳",
                "BGName": "TME",
                "ProductName": "",
                "CategoryName": "技术",
                "Responsibility": "负责音乐spider服务架构的设计和开发工作；\n设计各种策略和算法，提升spider的抓取效果；\n分析spider的技术缺陷，对spider做出合理地调整或改进；\n研究各种网站、网页、链接的形态，发现它们的特点和规律。",
                "LastUpdateTime": "2019年09月23日",
                "PostURL": "http://careers.tencent.com/jobdesc.html?postId=1163296010936520704",
                "SourceID": 1,
                "IsCollect": false,
                "IsValid": true
            },
            {
                "Id": 0,
                "PostId": "1161635128967958528",
                "RecruitPostId": 52597,
                "RecruitPostName": "25923-Python后台研发工程师（深圳）",
                "CountryName": "中国",
                "LocationName": "深圳",
                "BGName": "IEG",
                "ProductName": "",
                "CategoryName": "技术",
                "Responsibility": "负责腾讯运营安全微服务架构平台开发；\n负责腾讯运营安全海外平台开发；\n负责腾讯运营安全策略引擎开发。",
                "LastUpdateTime": "2019年08月14日",
                "PostURL": "http://careers.tencent.com/jobdesc.html?postId=0",
                "SourceID": 1,
                "IsCollect": false,
                "IsValid": true
            },
            {
                "Id": 0,
                "PostId": "1182229259981164544",
                "RecruitPostId": 54091,
                "RecruitPostName": "32271-增长策略产品经理（广告系统方向）",
                "CountryName": "中国",
                "LocationName": "北京",
                "BGName": "PCG",
                "ProductName": "",
                "CategoryName": "产品",
                "Responsibility": "数据驱动，参与目标的制定与拆分，负责腾讯视频的用户增长、留存、拉新、转化、ARPU 提升等产品设计，策略制定工作。 \n与设计、开发人员高效合作，从产品概念策划到推动开发上线中起到关键角色，对增长目标负责。 \n与运营、市场人员紧密配合， 推动营销策略的实施,发现助力业务拓展的机会点\n对所负责的项目进行数据跟踪与数据分析，并结合客户研究及竞品调研，找到对应的提升方案。",
                "LastUpdateTime": "2019年10月23日",
                "PostURL": "http://careers.tencent.com/jobdesc.html?postId=1182229259981164544",
                "SourceID": 1,
                "IsCollect": false,
                "IsValid": true
            }
        ]
    }
}